tkitAttNLocal/__init__.py
tkitAttNLocal/attnlocal.py
tkitAttNLocal-0.0.0.316336997.dist-info/LICENSE
tkitAttNLocal-0.0.0.316336997.dist-info/METADATA
tkitAttNLocal-0.0.0.316336997.dist-info/WHEEL
tkitAttNLocal-0.0.0.316336997.dist-info/top_level.txt
tkitAttNLocal-0.0.0.316336997.dist-info/RECORD
