Metadata-Version: 2.1
Name: tkitAttNLocal
Version: 0.0.0.316336997
Summary: Terry toolkit tkitAttNLocal,
Home-page: https://www.terrychan.org/
Author: Terry Chan
Author-email: napoler2008@gmail.com
License: UNKNOWN
Platform: UNKNOWN
Requires-Dist: pytorch-lightning (>=1.4.0)
